Mohit_STT01/__init__.py
Mohit_STT01/index.html
Mohit_STT01/input.txt
Mohit_STT01/script.js
Mohit_STT01/style.css
Mohit_STT01-0.1.dist-info/METADATA
Mohit_STT01-0.1.dist-info/WHEEL
Mohit_STT01-0.1.dist-info/top_level.txt
Mohit_STT01-0.1.dist-info/RECORD
